{
  "ignorePatterns": [
    {
      "pattern": "^http://localhost"
    },
    {
      "pattern": "^https://localhost"
    },
    {
      "pattern": "mailto:"
    },
    {
      "pattern": "github.com/reddygautam98/GenETL/discussions"
    },
    {
      "pattern": "docs/API_REFERENCE.md"
    },
    {
      "pattern": "docs/AI_FEATURES.md"
    },
    {
      "pattern": "docs/ai/"
    }
  ],
  "replacementPatterns": [],
  "httpHeaders": [],
  "timeout": "20s",
  "retryOn429": true,
  "retryCount": 3,
  "fallbackHttpStatus": [400, 401, 403, 404, 429, 500, 502, 503, 504],
  "aliveStatusCodes": [200, 302]
}